mgmscraper/__init__.py
mgmscraper/core/__init__.py
mgmscraper/core/http_client.py
mgmscraper/services/__init__.py
mgmscraper/services/daily_stats.py
mgmscraper/services/forecasts.py
mgmscraper/services/monthly_stats.py
mgmscraper/services/observations.py
mgmscraper/services/radar.py
mgmscraper/services/stations.py
mgmscraper-0.1.0.dist-info/licenses/LICENSE
mgmscraper-0.1.0.dist-info/METADATA
mgmscraper-0.1.0.dist-info/WHEEL
mgmscraper-0.1.0.dist-info/top_level.txt
mgmscraper-0.1.0.dist-info/RECORD
