Metadata-Version: 2.4
Name: mgmscraper
Version: 0.1.0
Summary: Asynchronous Python library for accessing Turkish Meteorology General Directorate (MGM) data
Author-email: Muhammed Ali Subaşı <mhmmdlsubasi@gmail.com>
License: MIT
Project-URL: Homepage, https://github.com/mhmmdlsubasi/mgmscraper
Project-URL: Documentation, https://mhmmdlsubasi.github.io/mgmscraper
Project-URL: Repository, https://github.com/mhmmdlsubasi/mgmscraper
Project-URL: Issues, https://github.com/mhmmdlsubasi/mgmscraper/issues
Keywords: mgmscraper,turkey-meteorology,async-weather-api,meteorological-data,weather-scraping,aiohttp-scraper,climate-analytics,national-weather-service,data-extraction,turkish-meteorology
Requires-Python: >=3.8
License-File: LICENSE
Requires-Dist: aiohttp>=3.8
Requires-Dist: beautifulsoup4>=4.9
Dynamic: license-file
